{"stations": { "stationsArray" : [
  [
    { "lat" : 51.612759500713814, "lng" : -0.2739265515827954, "name" : "Edgware", "code" : "EDG" },
    { "lat" : 51.60180324126749, "lng" : -0.26278877313272025, "name" : "Burnt Oak", "code" : "BUR" },
    { "lat" : 51.59439818791392, "lng" : -0.2486320331875017, "name" : "Colindale", "code" : "COL" },
    { "lat" : 51.58236686207079, "lng" : -0.22599785530692493, "name" : "Hendon Central", "code" : "HND" },
    { "lat" : 51.57587823838149, "lng" : -0.21326038205123482, "name" : "Brent Cross", "code" : "BTX" },
    { "lat" : 51.571075022581766, "lng" : -0.19324391235724395, "name" : "Golders Green", "code" : "GGR" },
    { "lat" : 51.555550280361246, "lng" : -0.17798941486352943, "name" : "Hampstead", "code" : "HMP" },
    { "lat" : 51.54993278359263, "lng" : -0.1637885084200872, "name" : "Belsize Park", "code" : "BPK" },
    { "lat" : 51.54346026274685, "lng" : -0.15251042560165337, "name" : "Chalk Farm", "code" : "CHF" },
    { "lat" : 51.538784225323035, "lng" : -0.1411622995186106, "name" : "Camden Town", "code" : "CTN" },
    { "lat" : 51.533345889181625, "lng" : -0.13849984534815524, "name" : "Mornington Crescent", "code" : "MCR" },
    { "lat" : 51.52786165455812, "lng" : -0.13295618866225375, "name" : "Euston", "code" : "EUS" },
    { "lat" : 51.52343653175133, "lng" : -0.13746234322554243, "name" : "Warren Street", "code" : "WST" },
    { "lat" : 51.51977273121197, "lng" : -0.1332870729628562, "name" : "Goodge Street", "code" : "GST" },
    { "lat" : 51.51613175879326, "lng" : -0.13055300526849062, "name" : "Tottenham Court Road", "code" : "TCR" },
    { "lat" : 51.510693188019395, "lng" : -0.1278930727310078, "name" : "Leicester Square", "code" : "LSQ" },
    { "lat" : 51.50610723927896, "lng" : -0.12231642985980562, "name" : "Charing Cross", "code" : "CHX" },
    { "lat" : 51.506084169141225, "lng" : -0.12087621670808957, "name" : "Embankment", "code" : "EMB" },
    { "lat" : 51.502350330873, "lng" : -0.11238357206050469, "name" : "Waterloo", "code" : "WLO" },
    { "lat" : 51.48693202151761, "lng" : -0.10437714782714427, "name" : "Kennington", "code" : "KEN" },
    { "lat" : 51.48078000041125, "lng" : -0.11327448941998129, "name" : "Oval", "code" : "OVL" },
    { "lat" : 51.47193095937269, "lng" : -0.12228016999043657, "name" : "Stockwell", "code" : "STK" },
    { "lat" : 51.463934044082215, "lng" : -0.1283678300817135, "name" : "Clapham North", "code" : "CPN" },
    { "lat" : 51.461375226703524, "lng" : -0.1371110334532604, "name" : "Clapham Common", "code" : "CPC" },
    { "lat" : 51.451648198320164, "lng" : -0.14758316691946552, "name" : "Clapham South", "code" : "CPS" },
    { "lat" : 51.44270573172805, "lng" : -0.15082341546665967, "name" : "Balham", "code" : "BAL" },
    { "lat" : 51.43472981353174, "lng" : -0.15834010401347612, "name" : "Tooting Bec", "code" : "TBE" },
    { "lat" : 51.42587706872216, "lng" : -0.16732787145007202, "name" : "Tooting Broadway", "code" : "TBY" },
    { "lat" : 51.41792239493648, "lng" : -0.17627635994525884, "name" : "Colliers Wood", "code" : "CLW" },
    { "lat" : 51.41454997169695, "lng" : -0.19079327811169472, "name" : "South Wimbledon", "code" : "SWM" },
    { "lat" : 51.40201087522883, "lng" : -0.19416396369664754, "name" : "Morden", "code" : "MOR" }
  ],
  [
    { "lat" : 51.65023487997356, "lng" : -0.19443478021389068, "name" : "High Barnet", "code" : "HBT" },
    { "lat" : 51.62929516483202, "lng" : -0.1779258124312763, "name" : "Totteridge & Whetstone", "code" : "TOT" },
    { "lat" : 51.61680177229409, "lng" : -0.18420493612312638, "name" : "Woodside Park", "code" : "WSP" },
    { "lat" : 51.608757361121604, "lng" : -0.18741478863739983, "name" : "West Finchley", "code" : "WFY" },
    { "lat" : 51.59981405415956, "lng" : -0.19065920302345754, "name" : "Finchley Central", "code" : "FYC" },
    { "lat" : 51.586805252379435, "lng" : -0.16374573101066248, "name" : "East Finchley", "code" : "EFY" },
    { "lat" : 51.57662381385878, "lng" : -0.14539214837171116, "name" : "Highgate", "code" : "HIG" },
    { "lat" : 51.564756933384565, "lng" : -0.13433101972225706, "name" : "Archway", "code" : "ARC" },
    { "lat" : 51.55581510389661, "lng" : -0.13758246222847634, "name" : "Tufnell Park", "code" : "TPK" },
    { "lat" : 51.54954660911795, "lng" : -0.1392810476934105, "name" : "Kentish Town", "code" : "KTN" },
    { "lat" : 51.538784225323035, "lng" : -0.1411622995186106, "name" : "Camden Town", "code" : "CTN" }
  ],
  [
    { "lat" : 51.538784225323035, "lng" : -0.1411622995186106, "name" : "Camden Town", "code" : "CTN" },
    { "lat" : 51.52786165455812, "lng" : -0.13295618866225375, "name" : "Euston", "code" : "EUS" },
    { "lat" : 51.530396948130495, "lng" : -0.12275894733267313, "name" : "King's Cross St. Pancras", "code" : "KXX" },
    { "lat" : 51.53191641970237, "lng" : -0.10539267723743864, "name" : "Angel", "code" : "ANG" },
    { "lat" : 51.52534460123317, "lng" : -0.08836422922894646, "name" : "Old Street", "code" : "OLD" },
    { "lat" : 51.51725588224769, "lng" : -0.08870298288929475, "name" : "Moorgate", "code" : "MGT" },
    { "lat" : 51.51273866130698, "lng" : -0.08745071594037705, "name" : "Bank", "code" : "BNK" },
    { "lat" : 51.504649929216434, "lng" : -0.0877894786379847, "name" : "London Bridge", "code" : "LON" },
    { "lat" : 51.500249966172134, "lng" : -0.09373761925247598, "name" : "Borough", "code" : "BOR" },
    { "lat" : 51.494950930139325, "lng" : -0.0997219954555799, "name" : "Elephant & Castle", "code" : "ELE" },
    { "lat" : 51.48693202151761, "lng" : -0.10437714782714427, "name" : "Kennington", "code" : "KEN" }
  ],
]}}